open_geodata/__init__.py
open_geodata/_version.py
open_geodata/functions.py
open_geodata/geo.py
open_geodata/br/__init__.py
open_geodata/converts/__init__.py
open_geodata/converts/coords.py
open_geodata/converts/coords_lixo.py
open_geodata/converts/files.py
open_geodata/folium_plus/__init__.py
open_geodata/folium_plus/adds.py
open_geodata/folium_plus/png.py
open_geodata/lyr/__init__.py
open_geodata/lyr/base.py
open_geodata/lyr/colors.py
open_geodata/sidra/__init__.py
open_geodata/sidra/ibge.py
open_geodata/sp/__init__.py
open_geoodata-0.1.0.dist-info/licenses/LICENSE
open_geoodata-0.1.0.dist-info/METADATA
open_geoodata-0.1.0.dist-info/WHEEL
open_geoodata-0.1.0.dist-info/top_level.txt
open_geoodata-0.1.0.dist-info/RECORD
