Metadata-Version: 2.4
Name: open-geoodata
Version: 0.1.0
Summary: Add your description here
Requires-Python: >=3.11
License-File: LICENSE
Requires-Dist: folium>=0.19.7
Requires-Dist: geopandas>=1.1.0
Requires-Dist: pandas>=2.3.0
Requires-Dist: py7zr>=1.0.0
Requires-Dist: selenium>=4.33.0
Requires-Dist: sidrapy>=0.1.4
Dynamic: license-file
